setup.cfg
setup.py
RPi_GPIO_Rotary/__init__.py
RPi_GPIO_Rotary/rotary.py
RPi_GPIO_Rotary.egg-info/PKG-INFO
RPi_GPIO_Rotary.egg-info/SOURCES.txt
RPi_GPIO_Rotary.egg-info/dependency_links.txt
RPi_GPIO_Rotary.egg-info/requires.txt
RPi_GPIO_Rotary.egg-info/top_level.txt